Metadata-Version: 2.1
Name: odoo12-addon-base-repair
Version: 12.0.1.1.1
Summary: This module extends the functionality of Odoo Repair module to add some basic features.
Home-page: https://github.com/OCA/manufacture
Author: Escodoo, Agile Business Group, Odoo Community Association (OCA)
Author-email: support@odoo-community.org
License: AGPL-3
Platform: UNKNOWN
Classifier: Programming Language :: Python
Classifier: Framework :: Odoo
Classifier: Framework :: Odoo :: 12.0
Classifier: License :: OSI Approved :: GNU Affero General Public License v3
Requires-Python: >=3.5
Requires-Dist: odoo (<12.1dev,>=12.0a)
